python_sei/__init__.py
python_sei/client.py
python_sei/models.py
python_sei/sin.py
python_sei-0.1.4.dist-info/METADATA
python_sei-0.1.4.dist-info/WHEEL
python_sei-0.1.4.dist-info/licenses/LICENSE
python_sei-0.1.4.dist-info/RECORD
