Metadata-Version: 2.4
Name: python_sei
Version: 0.1.4
Summary: Client em Python da API do SEI v4
Project-URL: Homepage, https://github.com/automatiza-mg/sei
Project-URL: Issues, https://github.com/automatiza-mg/sei/issues
Author-email: Felipe Felix Souza dos Santos <felipefelix2704@gmail.com>
License: Copyright (c) 2025 Secretaria de Estado de Planejamento e Gestão
License-File: LICENSE
Keywords: client,sei
Requires-Python: >=3.12
Requires-Dist: zeep
